zmp_openapi_toolkit/__init__.py
zmp_openapi_toolkit/toolkits/toolkit.py
zmp_openapi_toolkit/tools/tool.py
zmp_openapi_toolkit-0.2.0.dist-info/LICENSE
zmp_openapi_toolkit-0.2.0.dist-info/METADATA
zmp_openapi_toolkit-0.2.0.dist-info/WHEEL
zmp_openapi_toolkit-0.2.0.dist-info/RECORD
