Metadata-Version: 2.3
Name: zmp-openapi-toolkit
Version: 0.2.0
Summary: This is a toolkit library for the LLM application using the multiple openapi specifications
License: MIT
Keywords: llm,toolkit,openapi
Author: Kilsoo Kang
Author-email: kilsoo75@gmail.com
Maintainer: Kilsoo Kang
Maintainer-email: kilsoo75@gmail.com
Requires-Python: >=3.11,<4.0
Classifier: License :: OSI Approved :: MIT License
Classifier: Programming Language :: Python :: 3
Classifier: Programming Language :: Python :: 3.11
Classifier: Programming Language :: Python :: 3.12
Classifier: Programming Language :: Python :: 3.13
Requires-Dist: colorlog (>=6.9.0,<7.0.0)
Requires-Dist: langchain (>=0.3.20,<0.4.0)
Requires-Dist: langchain-core (>=0.3.43,<0.4.0)
Requires-Dist: python-dotenv (>=1.0.1,<2.0.0)
Requires-Dist: zmp-openapi-helper (>=0.2.0,<0.3.0)
Project-URL: Bug Tracker, https://github.com/cloudz-mp/zmp-openapi-toolkit/issues
Project-URL: Documentation, https://github.com/cloudz-mp/zmp-openapi-toolkit
Project-URL: Homepage, https://github.com/cloudz-mp
Project-URL: Repository, https://github.com/cloudz-mp/zmp-openapi-toolkit
